openeo_udf/__init__.py
openeo_udf/api/__init__.py
openeo_udf/api/collection_base.py
openeo_udf/api/datacube.py
openeo_udf/api/feature_collection.py
openeo_udf/api/machine_learn_model.py
openeo_udf/api/run_code.py
openeo_udf/api/spatial_extent.py
openeo_udf/api/structured_data.py
openeo_udf/api/tools.py
openeo_udf/api/udf_data.py
openeo_udf/api/udf_signatures.py
openeo_udf/api/udf_wrapper.py
openeo_udf/functions/__init__.py
openeo_udf/functions/datacube_map_fabs.py
openeo_udf/functions/datacube_ndvi.py
openeo_udf/functions/datacube_pytorch_ml.py
openeo_udf/functions/datacube_reduce_time_mean.py
openeo_udf/functions/datacube_reduce_time_min_median_max.py
openeo_udf/functions/datacube_reduce_time_sum.py
openeo_udf/functions/datacube_sampling.py
openeo_udf/functions/datacube_sklearn_ml.py
openeo_udf/functions/datacube_statistics.py
openeo_udf/functions/feature_collections_buffer.py
openeo_udf/server/__init__.py
openeo_udf/server/config.py
openeo_udf/server/machine_learn_database.py
openeo_udf/server/tools.py
openeo_udf/server/udf.py
openeo_udf/server/data_model/__init__.py
openeo_udf/server/data_model/bounding_box_schema.py
openeo_udf/server/data_model/data_collection_schema.py
openeo_udf/server/data_model/datacube_schema.py
openeo_udf/server/data_model/machine_learn_schema.py
openeo_udf/server/data_model/metadata_schema.py
openeo_udf/server/data_model/model_example_creator.py
openeo_udf/server/data_model/simple_feature_collection_schema.py
openeo_udf/server/data_model/structured_data_schema.py
openeo_udf/server/data_model/udf_schemas.py
openeo_udf/server/data_model/variables_collection_schema.py
openeo_udf/server/data_model/examples/data_collection_with_datacube.json
openeo_udf/server/data_model/examples/data_collection_with_datacube_and_feature_collection.json
openeo_udf/server/data_model/examples/data_collection_with_datacube_and_feature_collection_schema.json
openeo_udf/server/data_model/examples/data_collection_with_datacube_schema.json
openeo_udf-1.0.0rc3.post1.dist-info/AUTHORS.rst
openeo_udf-1.0.0rc3.post1.dist-info/LICENSE.txt
openeo_udf-1.0.0rc3.post1.dist-info/METADATA
openeo_udf-1.0.0rc3.post1.dist-info/WHEEL
openeo_udf-1.0.0rc3.post1.dist-info/top_level.txt
openeo_udf-1.0.0rc3.post1.dist-info/RECORD
