Metadata-Version: 2.2
Name: openeo_udf
Version: 1.0.0rc3.post1
Summary: API to implement user defined functions in openEO, as well as a reference server implementation to execute them.
Home-page: https://github.com/Open-EO/openeo-udf/
Author: Soeren Gebbert
Author-email: soerengebbert@googlemai.com
License: apache
Platform: any
Classifier: Development Status :: 5 - Production/Stable
Classifier: Programming Language :: Python
Classifier: License :: OSI Approved :: Apache Software License
Classifier: Operating System :: OS Independent
License-File: LICENSE.txt
License-File: AUTHORS.rst
